pipeless_ai/__init__.py
pipeless_ai/core.py
pipeless_ai/lib/__init__.py
pipeless_ai/lib/app/app.py
pipeless_ai/lib/app/plugin.py
pipeless_ai/lib/config.py
pipeless_ai/lib/connection.py
pipeless_ai/lib/input/input.py
pipeless_ai/lib/logger.py
pipeless_ai/lib/messages.py
pipeless_ai/lib/output/output.py
pipeless_ai/lib/plugins.py
pipeless_ai/lib/singleton.py
pipeless_ai/lib/timer.py
pipeless_ai/lib/worker/inference/runtime.py
pipeless_ai/lib/worker/inference/utils.py
pipeless_ai/lib/worker/worker.py
pipeless_ai/models/__init__.py
pipeless_ai/models/tflite.py
pipeless_ai-0.1.19.dist-info/LICENSE
pipeless_ai-0.1.19.dist-info/METADATA
pipeless_ai-0.1.19.dist-info/WHEEL
pipeless_ai-0.1.19.dist-info/RECORD
