Metadata-Version: 2.1
Name: pipeless-ai
Version: 0.1.19
Summary: An open-source computer vision framework to create and deploy computer vision applications that scale in minutes
Home-page: https://pipeless.ai
License: Apache-2.0
Keywords: multimedia,framework,artificial-intelligence,pipeline,developer-tools,computer-vision,image-processing
Author: Miguel Angel Cabrera Minagorri
Author-email: devgorri@gmail.com
Requires-Python: >=3.10,<4.0
Classifier: License :: OSI Approved :: Apache Software License
Classifier: Programming Language :: Python :: 3
Classifier: Programming Language :: Python :: 3.10
Classifier: Programming Language :: Python :: 3.11
Provides-Extra: onnx-cpu
Provides-Extra: onnx-gpu
Requires-Dist: line-profiler (>=4.1.1,<5.0.0)
Requires-Dist: numpy (>=1.24.0,<1.25.0)
Requires-Dist: onnx (>=1.14.1,<2.0.0) ; extra == "onnx-cpu" or extra == "onnx-gpu"
Requires-Dist: onnxruntime (>=1.16.0,<2.0.0) ; extra == "onnx-cpu"
Requires-Dist: onnxruntime-gpu (>=1.16.0,<2.0.0) ; extra == "onnx-gpu"
Requires-Dist: opencv-python (>=4.8.0.76,<5.0.0.0)
Requires-Dist: pygobject (>=3.44.1,<4.0.0)
Requires-Dist: pynng (>=0.7.2,<0.8.0)
Requires-Dist: requests (>=2.31.0,<3.0.0)
Requires-Dist: rich (>=13.4.2,<14.0.0)
Project-URL: Documentation, https://github.com/pipeless-ai/pipeless
Project-URL: Repository, https://github.com/pipeless-ai/pipeless
